hpdex/__init__.py
hpdex/backend/__init__.py
hpdex/backend/bin/kernel.cp313-win_amd64.pyd
hpdex/backend/de_.py
hpdex/backend/kernel.pyi
hpdex/backend/mannwhitneyu_.py
hpdex/backend/pykernel_.py
hpdex/de.py
hpdex/stream.py
hpdex-1.0.1.dist-info/METADATA
hpdex-1.0.1.dist-info/WHEEL
hpdex-1.0.1.dist-info/licenses/LICENSE
hpdex-1.0.1.dist-info/RECORD
