Metadata-Version: 2.1
Name: hpdex
Version: 1.0.1
Summary: High-Performance Parallel Differential Expression Analysis for Single-Cell Data
Keywords: single-cell,differential expression,pybind11,parallel,C++
Author-Email: Wang Zhongqi <2868116803@qq.com>
License: MIT
Requires-Python: >=3.10
Requires-Dist: numpy
Requires-Dist: scipy
Requires-Dist: numba
Requires-Dist: pandas
Requires-Dist: anndata
Requires-Dist: tqdm
Provides-Extra: test
Requires-Dist: scanpy; extra == "test"
Requires-Dist: pdex; extra == "test"
